tkreadonly.py
tkreadonly-0.6.1.dist-info/DESCRIPTION.rst
tkreadonly-0.6.1.dist-info/METADATA
tkreadonly-0.6.1.dist-info/RECORD
tkreadonly-0.6.1.dist-info/WHEEL
tkreadonly-0.6.1.dist-info/metadata.json
tkreadonly-0.6.1.dist-info/top_level.txt
